Metadata-Version: 2.2
Name: pastml
Version: 1.9.51
Summary: Ancestral character reconstruction and visualisation for rooted phylogenetic trees.
Home-page: https://github.com/evolbioinfo/pastml
Author: Anna Zhukova
Author-email: anna.zhukova@pasteur.fr
Keywords: PASTML,visualisation,phylogeny,ancestral character reconstruction
Classifier: Development Status :: 5 - Production/Stable
Classifier: Environment :: Console
Classifier: Intended Audience :: Developers
Classifier: Intended Audience :: Science/Research
Classifier: Topic :: Scientific/Engineering :: Bio-Informatics
Classifier: Topic :: Software Development :: Libraries :: Python Modules
Classifier: Programming Language :: Python :: 3
Classifier: Programming Language :: Python :: 3.9
Classifier: Programming Language :: Python :: 3.10
Classifier: Programming Language :: Python :: 3 :: Only
Requires-Python: >=3.10
License-File: LICENSE
Requires-Dist: ete3>=3.1.1
Requires-Dist: pandas>=1.0.0
Requires-Dist: numpy>=1.22
Requires-Dist: jinja2>=2.11.0
Requires-Dist: scipy==1.14.0
Requires-Dist: itolapi>=4.0.0
Requires-Dist: biopython>=1.70
Dynamic: author
Dynamic: author-email
Dynamic: classifier
Dynamic: description
Dynamic: description-content-type
Dynamic: home-page
Dynamic: keywords
Dynamic: requires-dist
Dynamic: requires-python
Dynamic: summary
